gym_tictactoe/__init__.py
gym_tictactoe/envs/__init__.py
gym_tictactoe/envs/tictactoe_env.py
gym_tictactoe/envs/tictactoe_plt_env.py
gym_tictactoe-0.30.dist-info/METADATA
gym_tictactoe-0.30.dist-info/WHEEL
gym_tictactoe-0.30.dist-info/top_level.txt
gym_tictactoe-0.30.dist-info/RECORD
