Metadata-Version: 2.1
Name: gym-tictactoe
Version: 0.30
Summary: Tic-Tac-Toe environment in OpenAI gym
Home-page: https://github.com/shkreza/gym-tictactoe
Author: Reza Sherafat
Author-email: sherafat.us@gmail.com
License: UNKNOWN
Platform: UNKNOWN
Classifier: Programming Language :: Python :: 3
Classifier: License :: OSI Approved :: MIT License
Classifier: Operating System :: OS Independent
Requires-Dist: gym
Requires-Dist: matplotlib
Requires-Dist: numpy
